setup.py
g2gchat/__init__.py
g2gchat/config_parser.py
g2gchat/g2gchat.py
g2gchat.egg-info/PKG-INFO
g2gchat.egg-info/SOURCES.txt
g2gchat.egg-info/dependency_links.txt
g2gchat.egg-info/top_level.txt