Metadata-Version: 1.0
Name: g2gchat
Version: 0.5.4
Summary: A Messenger for globalites with features including file transfer, backup of chat sessions and more...
Home-page: UNKNOWN
Author: Srikanth,Lalith
Author-email: rs.chemikala@globaledgesoft.com
License: UNKNOWN
Keywords: g2gchat,chat,multichat
Platform: UNKNOWN
